{
    "club_key": "china-114",
    "title": "盐工橘柚视觉小说同好会",
    "summary": "盐城工学院_盐工橘柚视觉小说同好会 是登记在 Galgame 同好会地图中的高校同好会之一。",
    "infobox": {
        "学校": "盐城工学院",
        "地区": "江苏省",
        "类型": "高校同好会",
        "成立时间": "2023\/10\/14",
        "状态": "已认证",
        "初代会长": "风涧月",
        "现任会长": "kokubun",
        "形象角色": "橘小柚"
    },
    "sections": [
        {
            "heading": "盐城工学院橘柚视觉小说同好会",
            "body": [
                "本页面用于整理该盐城工学院橘柚视觉小说同好会，简称橘柚视觉小说同好会或橘柚 galgame 同好会，是以盐城工学院学生为核心、围绕视觉小说与 galgame 交流而形成的校园同好团体。其英文名为 Visual Novel Circle of YCIT，同好会形象角色为橘小柚。",
                "同好会成立于 2023 年秋季学期，最初由校内几位视觉小说爱好者通过校园墙、群聊等渠道聚集而成。起初的想法很简单：找到更多能够一起聊 galgame、分享作品、交流感想的同好。随着成员数量增加，橘柚逐渐从一个兴趣交流群，发展为会定期组织活动、制作刊物、参与跨校交流的校园视觉小说同好团体。",
                "橘柚的主要活动包括作品主题月、校内“十二盐器”评选、年度萌战、视觉小说采访企划、线下团建、视觉小说研讨会、同好会刊物制作以及与其他高校同好会的交流活动。其中，“十二盐器”与“萌战”是同好会较有代表性的年度活动。前者通过成员投票选出当年较受欢迎的视觉小说作品，并围绕入选作品制作纪念视频、徽章、色纸等内容；后者则以角色人气投票为核心，并衍生出采访式视觉小说等创作企划。",
                "除日常讨论与活动外，橘柚也较重视“留下记录”。同好会曾制作迎新刊、二周年纪念群刊等刊物，用于介绍同好会、记录成员文章、整理活动照片与发展历程。2025 年，橘柚还参与了中日高校视觉小说同好会合同本企划，与多所中国及日本高校视觉小说相关社团共同完成以社团活动史和视觉小说未来为主题的交流刊物。",
                "在对外交流方面，橘柚与多所高校视觉小说、galgame 或 ACG 相关同好会保持联系，并曾参与或组织跨校交流、线下聚会、联合活动等。相比单纯的作品讨论群，橘柚更接近一个以视觉小说为中心的校园兴趣平台：成员可以在这里讨论作品、推荐游戏、学习视频与图像制作、尝试视觉小说开发，也可以参与刊物、周边、活动策划等企划。",
                "同好会目前主要通过 Bilibili 与 X 等平台进行公开发布。Bilibili 账号主要用于发布活动纪念视频、评选结果及相关宣传内容；X 账号则用于记录部分活动动态、刊物进度、推荐内容与对外交流信息。",
                "整体而言，橘柚视觉小说同好会是一个由兴趣自然生长出来的校园同好团体。它既保留了普通同好群轻松聊天、自由分享的氛围，也逐渐形成了属于自己的活动传统与创作方向。对成员来说，橘柚不仅是讨论视觉小说的地方，也是一个能够一起做点有趣事情、把共同爱好变成实际成果的空间。同好会的公开资料、发展历史、活动记录和对外链接。"
            ]
        },
        {
            "heading": "主要活动",
            "body": [
                "橘柚的活动大致可以分为作品讨论、年度评选、创作企划和线下交流几类。",
                "十二盐器是同好会秋季学期的重要活动。成员通过提名和投票选出 12 部较受欢迎的视觉小说作品，最终结果会被整理为榜单，并制作纪念视频、海报、徽章或色纸等内容。",
                "年度萌战通常在春季学期举行，以视觉小说角色人气投票为核心。活动结束后，同好会会围绕入选角色进行采访、文本整理，并尝试制作成视觉小说形式的企划内容。",
                "同好会刊物是橘柚较有代表性的创作方向之一。刊物内容包括成员文章、作品推荐、活动回顾、插画、友校祝福和同好会发展记录等。二周年纪念群刊是目前较系统整理同好会发展历程的成果之一。",
                "线下交流与团建则包括聚餐、KTV、跨校交流、活动摆摊等。通过这些活动，橘柚从线上兴趣群逐渐扩展到真实校园生活之中。"
            ]
        },
        {
            "heading": "特色",
            "body": [
                "橘柚的特点在于它并不只停留在“聊天”层面，而是会把成员的兴趣转化为具体的活动和作品。无论是榜单、视频、徽章、刊物，还是采访式视觉小说，都是同好会成员共同参与后的成果。",
                "同时，橘柚也带有比较强的校园社群色彩。它不像商业社团，也不是严格意义上的制作组，而更像是一群学生因为共同爱好聚在一起后，慢慢摸索出来的开放空间。这里既可以认真讨论作品，也可以轻松闲聊；既可以做活动，也可以单纯分享自己喜欢的游戏和角色。"
            ]
        }
    ],
    "images": [
        {
            "url": "..\/uploads\/china-114\/20260515024009_0d31e26a.png?t=1778784009",
            "caption": "同好会头像",
            "alt": "YCIT-small",
            "width_percent": 50,
            "aspect_ratio": "1\/1",
            "align": "left",
            "fit": "cover"
        }
    ],
    "references": [
        {
            "label": "Bilibili",
            "url": "https:\/\/space.bilibili.com\/3546557003598336\/"
        },
        {
            "label": "X",
            "url": "https:\/\/x.com\/Ycitgalgame"
        }
    ],
    "updated_at": "2026-05-15"
}